<?xml version="1.0" encoding="UTF-8"?><record_update>
    <sys_choice action="DELETE" field="u_request_type" table="x_58872_needit_needit" version="3">
        <sys_choice_set action="DELETE">
            <element>u_request_type</element>
            <name>x_58872_needit_needit</name>
            <sys_class_name/>
            <sys_created_by>admin</sys_created_by>
            <sys_created_on/>
            <sys_id>5883bab3db1c10109a2eb08039961926</sys_id>
            <sys_mod_count/>
            <sys_name>u_request_type</sys_name>
            <sys_package display_value="NeedIt" source="x_58872_needit">6ead8e780f603200cd674f8ce1050ed1</sys_package>
            <sys_policy/>
            <sys_scope display_value="NeedIt">6ead8e780f603200cd674f8ce1050ed1</sys_scope>
            <sys_update_name>sys_choice_x_58872_needit_needit_u_request_type</sys_update_name>
            <sys_updated_by>admin</sys_updated_by>
            <sys_updated_on>2020-04-28 13:23:31</sys_updated_on>
        </sys_choice_set>
        <sys_update_version action="INSERT_OR_UPDATE">
            <action>DELETE</action>
            <application/>
            <file_path/>
            <instance_id>676826c2db29fb040b9d21c40596194a</instance_id>
            <instance_name>dev86302</instance_name>
            <name>sys_choice_x_58872_needit_needit_u_request_type</name>
            <payload><![CDATA[<?xml version="1.0" encoding="UTF-8"?><record_update><sys_choice action="DELETE" field="u_request_type" table="x_58872_needit_needit" version="3"><sys_choice_set action="DELETE"><element>u_request_type</element><name>x_58872_needit_needit</name><sys_class_name/><sys_created_by/><sys_created_on/><sys_id/><sys_mod_count/><sys_name/><sys_package/><sys_policy/><sys_scope/><sys_update_name/><sys_updated_by/><sys_updated_on>2020-04-27 22:06:41</sys_updated_on></sys_choice_set></sys_choice></record_update>]]></payload>
            <payload_hash>1828161538</payload_hash>
            <record_name>x_58872_needit_needit.u_request_type</record_name>
            <reverted_from/>
            <source>2d73b233db1c10109a2eb08039961932</source>
            <source_table>sys_update_set</source_table>
            <state>previous</state>
            <sys_created_by>admin</sys_created_by>
            <sys_created_on>2020-04-27 22:06:41</sys_created_on>
            <sys_id>b2733ab3db1c10109a2eb080399619cc</sys_id>
            <sys_mod_count>0</sys_mod_count>
            <sys_recorded_at>171bdad94750000001</sys_recorded_at>
            <sys_updated_by>admin</sys_updated_by>
            <sys_updated_on>2020-04-27 22:06:41</sys_updated_on>
            <type>Choice list</type>
            <update_guid>3e733ab3441c101073c2eb18aba300cb</update_guid>
            <update_guid_history>3e733ab3441c101073c2eb18aba300cb:1828161538,f6733ab3e31c10106d86678fac1560c8:-103233526,7a733ab3a41c1010da1d826162c18f93:-854501905,f6733ab3371c1010cb7c757b401f7a90:878753447,8a63b6b3551c10104b585bae73154f0f:0,5f53f2b3001c10101d95ef247eebfe42:129573200,df53f2b3e41c1010095a25b7c29e5c3e:-1701966180,5f53f2b3c01c1010c4cfc6a48d3f583b:736548692,db53f2b3471c1010a5cde59fadecce38:833312879,508fe6fff4d810103271db4902dc13ea:0,ce7f66ff01d81010a945bc2cdad02fe0:1828161538,b97f66ffeed81010af6111ff12e06edd:-103233526,397f66ffcbd810108c601968da6911da:-854501905,b57f66ff36d81010a8cf4f26de6fd9d7:878753447,3c6fe2ff2cd81010b24f3bcee10b536c:0,025f22ff30d81010425055673066cda4:1179368059,825f22ffbad81010ffc0e1a39d7989a0:-1701966180,025f22ff33d810100ef131f1a7fd139d:736548692,8e5f22ff4bd8101048407d31ceb86699:833312879,234d52f380d81010db312504b279f17e:0,014ddeb371d810104a4427fd517ce050:1828161538,c94ddeb3a2d810104ce015587572364c:-103233526,494ddeb3c1d810101a8d83cc0392d949:-854501905,c54ddeb39ed810108a278fb7d641ce46:878753447,288156fb789810102d3024fbb4cf9ce0:411213506</update_guid_history>
        </sys_update_version>
        <sys_metadata_delete action="INSERT_OR_UPDATE">
            <sys_audit_delete/>
            <sys_class_name>sys_metadata_delete</sys_class_name>
            <sys_created_by>admin</sys_created_by>
            <sys_created_on>2020-04-27 22:06:50</sys_created_on>
            <sys_db_object display_value="" name="sys_choice_set">sys_choice_set</sys_db_object>
            <sys_id>5883bab3db1c10109a2eb08039961926</sys_id>
            <sys_metadata>5883bab3db1c10109a2eb08039961926</sys_metadata>
            <sys_mod_count>0</sys_mod_count>
            <sys_name>u_request_type</sys_name>
            <sys_package display_value="NeedIt" source="x_58872_needit">6ead8e780f603200cd674f8ce1050ed1</sys_package>
            <sys_parent/>
            <sys_policy/>
            <sys_scope display_value="NeedIt">6ead8e780f603200cd674f8ce1050ed1</sys_scope>
            <sys_scope_delete display_value="">94872a8897db403e8ee69a431de2fca4</sys_scope_delete>
            <sys_update_name>sys_choice_x_58872_needit_needit_u_request_type</sys_update_name>
            <sys_update_version display_value="sys_choice_x_58872_needit_needit_u_request_type">b2733ab3db1c10109a2eb080399619cc</sys_update_version>
            <sys_updated_by>admin</sys_updated_by>
            <sys_updated_on>2020-04-27 22:06:50</sys_updated_on>
        </sys_metadata_delete>
    </sys_choice>
    <sys_update_version action="INSERT_OR_UPDATE">
        <action>DELETE</action>
        <application display_value="NeedIt">6ead8e780f603200cd674f8ce1050ed1</application>
        <file_path/>
        <instance_id>676826c2db29fb040b9d21c40596194a</instance_id>
        <instance_name>dev86302</instance_name>
        <name>sys_choice_x_58872_needit_needit_u_request_type</name>
        <payload>&lt;?xml version="1.0" encoding="UTF-8"?&gt;&lt;record_update&gt;&lt;sys_choice action="DELETE" field="u_request_type" table="x_58872_needit_needit" version="3"&gt;&lt;sys_choice_set action="DELETE"&gt;&lt;element&gt;u_request_type&lt;/element&gt;&lt;name&gt;x_58872_needit_needit&lt;/name&gt;&lt;sys_class_name/&gt;&lt;sys_created_by&gt;admin&lt;/sys_created_by&gt;&lt;sys_created_on/&gt;&lt;sys_id&gt;5883bab3db1c10109a2eb08039961926&lt;/sys_id&gt;&lt;sys_mod_count/&gt;&lt;sys_name&gt;u_request_type&lt;/sys_name&gt;&lt;sys_package display_value="NeedIt" source="x_58872_needit"&gt;6ead8e780f603200cd674f8ce1050ed1&lt;/sys_package&gt;&lt;sys_policy/&gt;&lt;sys_scope display_value="NeedIt"&gt;6ead8e780f603200cd674f8ce1050ed1&lt;/sys_scope&gt;&lt;sys_update_name&gt;sys_choice_x_58872_needit_needit_u_request_type&lt;/sys_update_name&gt;&lt;sys_updated_by&gt;admin&lt;/sys_updated_by&gt;&lt;sys_updated_on&gt;2020-04-28 13:23:31&lt;/sys_updated_on&gt;&lt;/sys_choice_set&gt;&lt;sys_update_version action="INSERT_OR_UPDATE"&gt;&lt;action&gt;DELETE&lt;/action&gt;&lt;application/&gt;&lt;file_path/&gt;&lt;instance_id&gt;676826c2db29fb040b9d21c40596194a&lt;/instance_id&gt;&lt;instance_name&gt;dev86302&lt;/instance_name&gt;&lt;name&gt;sys_choice_x_58872_needit_needit_u_request_type&lt;/name&gt;&lt;payload&gt;&lt;![CDATA[&lt;?xml version="1.0" encoding="UTF-8"?&gt;&lt;record_update&gt;&lt;sys_choice action="DELETE" field="u_request_type" table="x_58872_needit_needit" version="3"&gt;&lt;sys_choice_set action="DELETE"&gt;&lt;element&gt;u_request_type&lt;/element&gt;&lt;name&gt;x_58872_needit_needit&lt;/name&gt;&lt;sys_class_name/&gt;&lt;sys_created_by/&gt;&lt;sys_created_on/&gt;&lt;sys_id/&gt;&lt;sys_mod_count/&gt;&lt;sys_name/&gt;&lt;sys_package/&gt;&lt;sys_policy/&gt;&lt;sys_scope/&gt;&lt;sys_update_name/&gt;&lt;sys_updated_by/&gt;&lt;sys_updated_on&gt;2020-04-27 22:06:41&lt;/sys_updated_on&gt;&lt;/sys_choice_set&gt;&lt;/sys_choice&gt;&lt;/record_update&gt;]]&gt;&lt;/payload&gt;&lt;payload_hash&gt;1828161538&lt;/payload_hash&gt;&lt;record_name&gt;x_58872_needit_needit.u_request_type&lt;/record_name&gt;&lt;reverted_from/&gt;&lt;source&gt;2d73b233db1c10109a2eb08039961932&lt;/source&gt;&lt;source_table&gt;sys_update_set&lt;/source_table&gt;&lt;state&gt;previous&lt;/state&gt;&lt;sys_created_by&gt;admin&lt;/sys_created_by&gt;&lt;sys_created_on&gt;2020-04-27 22:06:41&lt;/sys_created_on&gt;&lt;sys_id&gt;b2733ab3db1c10109a2eb080399619cc&lt;/sys_id&gt;&lt;sys_mod_count&gt;0&lt;/sys_mod_count&gt;&lt;sys_recorded_at&gt;171bdad94750000001&lt;/sys_recorded_at&gt;&lt;sys_updated_by&gt;admin&lt;/sys_updated_by&gt;&lt;sys_updated_on&gt;2020-04-27 22:06:41&lt;/sys_updated_on&gt;&lt;type&gt;Choice list&lt;/type&gt;&lt;update_guid&gt;3e733ab3441c101073c2eb18aba300cb&lt;/update_guid&gt;&lt;update_guid_history&gt;3e733ab3441c101073c2eb18aba300cb:1828161538,f6733ab3e31c10106d86678fac1560c8:-103233526,7a733ab3a41c1010da1d826162c18f93:-854501905,f6733ab3371c1010cb7c757b401f7a90:878753447,8a63b6b3551c10104b585bae73154f0f:0,5f53f2b3001c10101d95ef247eebfe42:129573200,df53f2b3e41c1010095a25b7c29e5c3e:-1701966180,5f53f2b3c01c1010c4cfc6a48d3f583b:736548692,db53f2b3471c1010a5cde59fadecce38:833312879,508fe6fff4d810103271db4902dc13ea:0,ce7f66ff01d81010a945bc2cdad02fe0:1828161538,b97f66ffeed81010af6111ff12e06edd:-103233526,397f66ffcbd810108c601968da6911da:-854501905,b57f66ff36d81010a8cf4f26de6fd9d7:878753447,3c6fe2ff2cd81010b24f3bcee10b536c:0,025f22ff30d81010425055673066cda4:1179368059,825f22ffbad81010ffc0e1a39d7989a0:-1701966180,025f22ff33d810100ef131f1a7fd139d:736548692,8e5f22ff4bd8101048407d31ceb86699:833312879,234d52f380d81010db312504b279f17e:0,014ddeb371d810104a4427fd517ce050:1828161538,c94ddeb3a2d810104ce015587572364c:-103233526,494ddeb3c1d810101a8d83cc0392d949:-854501905,c54ddeb39ed810108a278fb7d641ce46:878753447,288156fb789810102d3024fbb4cf9ce0:411213506&lt;/update_guid_history&gt;&lt;/sys_update_version&gt;&lt;sys_metadata_delete action="INSERT_OR_UPDATE"&gt;&lt;sys_audit_delete/&gt;&lt;sys_class_name&gt;sys_metadata_delete&lt;/sys_class_name&gt;&lt;sys_created_by&gt;admin&lt;/sys_created_by&gt;&lt;sys_created_on&gt;2020-04-27 22:06:50&lt;/sys_created_on&gt;&lt;sys_db_object display_value="" name="sys_choice_set"&gt;sys_choice_set&lt;/sys_db_object&gt;&lt;sys_id&gt;5883bab3db1c10109a2eb08039961926&lt;/sys_id&gt;&lt;sys_metadata&gt;5883bab3db1c10109a2eb08039961926&lt;/sys_metadata&gt;&lt;sys_mod_count&gt;0&lt;/sys_mod_count&gt;&lt;sys_name&gt;u_request_type&lt;/sys_name&gt;&lt;sys_package display_value="NeedIt" source="x_58872_needit"&gt;6ead8e780f603200cd674f8ce1050ed1&lt;/sys_package&gt;&lt;sys_parent/&gt;&lt;sys_policy/&gt;&lt;sys_scope display_value="NeedIt"&gt;6ead8e780f603200cd674f8ce1050ed1&lt;/sys_scope&gt;&lt;sys_scope_delete display_value=""&gt;94872a8897db403e8ee69a431de2fca4&lt;/sys_scope_delete&gt;&lt;sys_update_name&gt;sys_choice_x_58872_needit_needit_u_request_type&lt;/sys_update_name&gt;&lt;sys_update_version display_value="sys_choice_x_58872_needit_needit_u_request_type"&gt;b2733ab3db1c10109a2eb080399619cc&lt;/sys_update_version&gt;&lt;sys_updated_by&gt;admin&lt;/sys_updated_by&gt;&lt;sys_updated_on&gt;2020-04-27 22:06:50&lt;/sys_updated_on&gt;&lt;/sys_metadata_delete&gt;&lt;/sys_choice&gt;&lt;/record_update&gt;</payload>
        <payload_hash>-986997566</payload_hash>
        <record_name>x_58872_needit_needit.u_request_type</record_name>
        <reverted_from/>
        <source>f093b673db1c10109a2eb08039961998</source>
        <source_table>sys_update_set</source_table>
        <state>previous</state>
        <sys_created_by>admin</sys_created_by>
        <sys_created_on>2020-04-28 13:23:31</sys_created_on>
        <sys_id>3055428cdbe050109a2eb080399619a1</sys_id>
        <sys_mod_count>0</sys_mod_count>
        <sys_recorded_at>171c0f4f6a60000001</sys_recorded_at>
        <sys_updated_by>admin</sys_updated_by>
        <sys_updated_on>2020-04-28 13:23:31</sys_updated_on>
        <type>Choice list</type>
        <update_guid>b855428c53e050109a14213fa93143a0</update_guid>
        <update_guid_history>b855428c53e050109a14213fa93143a0:-986997566,3c55428ceee050107f68d060bcbd629c:-1701966180,b855428c5ce050107ea6f7edc9e1ad99:736548692,3855428cb3e05010251a483c17dd8d96:833312879,3083bab3e01c10103df025d8f666ccbb:0,3e733ab3441c101073c2eb18aba300cb:1828161538,f6733ab3e31c10106d86678fac1560c8:-103233526,7a733ab3a41c1010da1d826162c18f93:-854501905,f6733ab3371c1010cb7c757b401f7a90:878753447,8a63b6b3551c10104b585bae73154f0f:0,5f53f2b3001c10101d95ef247eebfe42:129573200,df53f2b3e41c1010095a25b7c29e5c3e:-1701966180,5f53f2b3c01c1010c4cfc6a48d3f583b:736548692,db53f2b3471c1010a5cde59fadecce38:833312879,508fe6fff4d810103271db4902dc13ea:0,ce7f66ff01d81010a945bc2cdad02fe0:1828161538,b97f66ffeed81010af6111ff12e06edd:-103233526,397f66ffcbd810108c601968da6911da:-854501905,b57f66ff36d81010a8cf4f26de6fd9d7:878753447,3c6fe2ff2cd81010b24f3bcee10b536c:0,025f22ff30d81010425055673066cda4:1179368059,825f22ffbad81010ffc0e1a39d7989a0:-1701966180,025f22ff33d810100ef131f1a7fd139d:736548692,8e5f22ff4bd8101048407d31ceb86699:833312879,234d52f380d81010db312504b279f17e:0,014ddeb371d810104a4427fd517ce050:1828161538,c94ddeb3a2d810104ce015587572364c:-103233526,494ddeb3c1d810101a8d83cc0392d949:-854501905,c54ddeb39ed810108a278fb7d641ce46:878753447,288156fb789810102d3024fbb4cf9ce0:411213506</update_guid_history>
    </sys_update_version>
    <sys_metadata_delete action="INSERT_OR_UPDATE">
        <sys_audit_delete/>
        <sys_class_name>sys_metadata_delete</sys_class_name>
        <sys_created_by>admin</sys_created_by>
        <sys_created_on>2020-04-28 13:23:41</sys_created_on>
        <sys_db_object display_value="" name="sys_choice_set">sys_choice_set</sys_db_object>
        <sys_id>3255c28cdbe050109a2eb0803996196d</sys_id>
        <sys_metadata>3255c28cdbe050109a2eb0803996196d</sys_metadata>
        <sys_mod_count>0</sys_mod_count>
        <sys_name>u_request_type</sys_name>
        <sys_package display_value="NeedIt" source="x_58872_needit">6ead8e780f603200cd674f8ce1050ed1</sys_package>
        <sys_parent/>
        <sys_policy/>
        <sys_scope display_value="NeedIt">6ead8e780f603200cd674f8ce1050ed1</sys_scope>
        <sys_scope_delete display_value="">94872a8897db403e8ee69a431de2fca4</sys_scope_delete>
        <sys_update_name>sys_choice_x_58872_needit_needit_u_request_type</sys_update_name>
        <sys_update_version display_value="sys_choice_x_58872_needit_needit_u_request_type">3055428cdbe050109a2eb080399619a1</sys_update_version>
        <sys_updated_by>admin</sys_updated_by>
        <sys_updated_on>2020-04-28 13:23:41</sys_updated_on>
    </sys_metadata_delete>
</record_update>
